traccar_api_client/__init__.py
traccar_api_client/client.py
traccar_api_client/errors.py
traccar_api_client/py.typed
traccar_api_client/types.py
traccar_api_client/api/__init__.py
traccar_api_client/api/attributes/__init__.py
traccar_api_client/api/attributes/delete_attributes_computed_id.py
traccar_api_client/api/attributes/get_attributes_computed.py
traccar_api_client/api/attributes/post_attributes_computed.py
traccar_api_client/api/attributes/put_attributes_computed_id.py
traccar_api_client/api/calendars/__init__.py
traccar_api_client/api/calendars/delete_calendars_id.py
traccar_api_client/api/calendars/get_calendars.py
traccar_api_client/api/calendars/post_calendars.py
traccar_api_client/api/calendars/put_calendars_id.py
traccar_api_client/api/commands/__init__.py
traccar_api_client/api/commands/delete_commands_id.py
traccar_api_client/api/commands/get_commands.py
traccar_api_client/api/commands/get_commands_send.py
traccar_api_client/api/commands/get_commands_types.py
traccar_api_client/api/commands/post_commands.py
traccar_api_client/api/commands/post_commands_send.py
traccar_api_client/api/commands/put_commands_id.py
traccar_api_client/api/devices/__init__.py
traccar_api_client/api/devices/delete_devices_id.py
traccar_api_client/api/devices/get_devices.py
traccar_api_client/api/devices/post_devices.py
traccar_api_client/api/devices/put_devices_id.py
traccar_api_client/api/devices/put_devices_id_accumulators.py
traccar_api_client/api/drivers/__init__.py
traccar_api_client/api/drivers/delete_drivers_id.py
traccar_api_client/api/drivers/get_drivers.py
traccar_api_client/api/drivers/post_drivers.py
traccar_api_client/api/drivers/put_drivers_id.py
traccar_api_client/api/events/__init__.py
traccar_api_client/api/events/get_events_id.py
traccar_api_client/api/geofences/__init__.py
traccar_api_client/api/geofences/delete_geofences_id.py
traccar_api_client/api/geofences/get_geofences.py
traccar_api_client/api/geofences/post_geofences.py
traccar_api_python_client-0.0.3.dist-info/licenses/LICENSE
traccar_api_python_client-0.0.3.dist-info/WHEEL
traccar_api_python_client-0.0.3.dist-info/METADATA
traccar_api_python_client-0.0.3.dist-info/RECORD
