Metadata-Version: 2.4
Name: traccar-api-python-client
Version: 0.0.3
Summary: A Python client for the Traccar API
Author-email: Kaboom Pixel <undisclosed@no-reply.email>
Requires-Python: >=3.10
Classifier: Development Status :: 3 - Alpha
Classifier: Intended Audience :: Developers
Classifier: License :: OSI Approved :: MIT License
Classifier: Operating System :: OS Independent
Classifier: Programming Language :: Python :: 3 :: Only
Classifier: Programming Language :: Python :: 3.10
Classifier: Programming Language :: Python :: 3.11
Classifier: Programming Language :: Python :: 3.12
Classifier: Programming Language :: Python :: 3.13
Classifier: Programming Language :: Python :: 3.14
Classifier: Topic :: Software Development :: Libraries :: Python Modules
License-File: LICENSE
Requires-Dist: httpx>=0.23.0,<0.29.0
Requires-Dist: attrs>=22.2.0
Requires-Dist: python-dateutil>=2.8.1
Project-URL: Documentation, https://github.com/kaboompixel/traccar-api-python-client/blob/main/README.md
Project-URL: Home, https://github.com/kaboompixel/traccar-api-python-client
Project-URL: Source, https://github.com/kaboompixel/traccar-api-python-client
Project-URL: Tracker, https://github.com/kaboompixel/traccar-api-python-client/issues
